lsy_testcase_to_xmind/__init__.py
lsy_testcase_to_xmind-0.1.0.dist-info/WHEEL
lsy_testcase_to_xmind-0.1.0.dist-info/entry_points.txt
lsy_testcase_to_xmind-0.1.0.dist-info/METADATA
lsy_testcase_to_xmind-0.1.0.dist-info/RECORD
