Metadata-Version: 2.3
Name: lsy-testcase-to-xmind
Version: 0.1.0
Summary: Add your description here
Author: NewBeeShiYuan
Author-email: NewBeeShiYuan <1933387865@qq.com>
Requires-Dist: mcp[cli]>=1.13.1
Requires-Python: >=3.13
